CHANGES.txt
MANIFEST.in
README.rst
requirements.txt
setup.py
silota/__init__.py
silota/__init__.pyc
silota/_config.py
silota/_config.pyc
silota/api.py
silota/api.pyc
silota/core.py
silota/core.pyc
silota/helpers.py
silota/helpers.pyc
silota/models.py
silota/models.pyc
silota/structures.py
silota/structures.pyc
silota.egg-info/PKG-INFO
silota.egg-info/SOURCES.txt
silota.egg-info/dependency_links.txt
silota.egg-info/requires.txt
silota.egg-info/top_level.txt