Metadata-Version: 1.1
Name: silota
Version: 0.0.4
Summary: Python client for the Silota Search As A Service API
Home-page: http://www.silota.com
Author: Ganesh Swami
Author-email: support@silota.com
License: BSD
Platform: UNKNOWN
Classifier: Intended Audience :: Developers
Classifier: License :: OSI Approved :: BSD License
Classifier: Programming Language :: Python
Classifier: Topic :: Software Development :: Libraries :: Python Modules
